{"cameraMode":{"drawMode":0,"name":"Shaded","section":"Shading Mode"},"sceneLighting":false,"audioPlay":false,"sceneViewState":{"m_AlwaysRefresh":false,"showFog":true,"showSkybox":false,"showFlares":true,"showImageEffects":true,"showParticleSystems":true,"showVisualEffectGraphs":true,"m_FxEnabled":true},"in2DMode":false,"pivot":{"x":-0.8767683506011963,"y":-0.4842020273208618,"z":7.621787071228027},"rotation":{"x":0.06714924424886704,"y":-0.0938497856259346,"z":0.006344563327729702,"w":0.9932976961135864},"size":3.6110548973083498,"orthographic":false}